stackable_plugins/__init__.py
stackable_plugins/abstract_models.py
stackable_plugins/admin.py
stackable_plugins/cms_plugins.py
stackable_plugins/config.py
stackable_plugins/helpers.py
stackable_plugins/mixins.py
stackable_plugins/models.py
stackable_plugins/utils.py
stackable_plugins/migrations/0001_initial.py
stackable_plugins/migrations/__init__.py
stackable_plugins/templates/README.md
stackable_plugins/templates/renderers_by_class/hosted_video/default.html
stackable_plugins/templates/renderers_by_class/rendered_biography/default.html
stackable_plugins/templates/renderers_by_class/rendered_button/default.html
stackable_plugins/templates/renderers_by_class/rendered_comparison/default.html
stackable_plugins/templates/renderers_by_class/rendered_countdown/default.html
stackable_plugins/templates/renderers_by_class/rendered_generic/accordion_container.html
stackable_plugins/templates/renderers_by_class/rendered_generic/default_generic_container.html
stackable_plugins/templates/renderers_by_class/rendered_image/default.html
stackable_plugins/templates/renderers_by_class/rendered_list/2_up.html
stackable_plugins/templates/renderers_by_class/rendered_list/3_up.html
stackable_plugins/templates/renderers_by_class/rendered_list/bulleted_list.html
stackable_plugins/templates/renderers_by_class/rendered_list/carousel.html
stackable_plugins/templates/renderers_by_class/rendered_list/default.html
stackable_plugins/templates/renderers_by_class/rendered_separator/default_generic_separator.html
stackable_plugins/templates/renderers_by_class/rendered_separator/image_separator.html
stackable_plugins/templates/renderers_by_class/rendered_text/default.html
djangocms_stackable_plugins-0.3.dist-info/LICENSE
djangocms_stackable_plugins-0.3.dist-info/METADATA
djangocms_stackable_plugins-0.3.dist-info/WHEEL
djangocms_stackable_plugins-0.3.dist-info/top_level.txt
djangocms_stackable_plugins-0.3.dist-info/RECORD
